[
  {
    "id": "faith",
    "title": "Monotheism (Tawhid)",
    "description": "The foundation of Islam: belief in the absolute oneness of Allah.",
    "image": "/assets/images/topics/faith.png",
    "verses": [
      { "surah": 112, "verse": 1, "title": "Al-Ikhlas (Oneness)" },
      { "surah": 2, "verse": 255, "title": "Ayat al-Kursi (The Throne)" },
      { "surah": 2, "verse": 163, "title": "One God" },
      { "surah": 3, "verse": 18, "title": "Witnessing Unity" },
      { "surah": 6, "verse": 102, "title": "The Creator" },
      { "surah": 59, "verse": 23, "title": "Names of Allah" },
      { "surah": 17, "verse": 111, "title": "No Partners" },
      { "surah": 23, "verse": 91, "title": "Divine Authority" },
      { "surah": 25, "verse": 2, "title": "Sovereign Control" },
      { "surah": 28, "verse": 70, "title": "He is Allah" },
      { "surah": 43, "verse": 84, "title": "God of Heavens" },
      { "surah": 16, "verse": 51, "title": "God is One" },
      { "surah": 64, "verse": 1, "title": "Glorification" },
      { "surah": 51, "verse": 56, "title": "Purpose" },
      { "surah": 39, "verse": 62, "title": "Sustainer" }
    ]
  },
  {
    "id": "patience",
    "title": "Patience & Gratitude",
    "description": "The spiritual virtues of Sabr and Shukr in times of trial and ease.",
    "image": "/assets/images/topics/patience.png",
    "verses": [
      { "surah": 2, "verse": 153, "title": "Seek help in Patience" },
      { "surah": 3, "verse": 200, "title": "Be Patient" },
      { "surah": 14, "verse": 7, "title": "Increase in Gratitude" },
      { "surah": 39, "verse": 10, "title": "Reward Without Measure" },
      { "surah": 94, "verse": 5, "title": "Ease with Hardship" },
      { "surah": 2, "verse": 45, "title": "Patience and Salah" },
      { "surah": 103, "verse": 3, "title": "Enjoin Persistence" },
      { "surah": 8, "verse": 46, "title": "Allah is with Patient" },
      { "surah": 16, "verse": 127, "title": "Patience from Allah" },
      { "surah": 3, "verse": 146, "title": "Steadfastness" },
      { "surah": 11, "verse": 11, "title": "Good deeds/Patience" },
      { "surah": 42, "verse": 43, "title": "Force of Character" },
      { "surah": 76, "verse": 24, "title": "Wait for Command" },
      { "surah": 90, "verse": 17, "title": "Patience & Compassion" },
      { "surah": 31, "verse": 17, "title": "Endure with Constancy" }
    ]
  },
  {
    "id": "social-justice",
    "title": "Social Justice & Ethics",
    "description": "Compassionate principles for fairness, honesty, and communal care.",
    "image": "/assets/images/topics/justice.png",
    "verses": [
      { "surah": 4, "verse": 135, "title": "Standing for Justice" },
      { "surah": 5, "verse": 8, "title": "Fairness even to Enemies" },
      { "surah": 16, "verse": 90, "title": "Justice and Kindness" },
      { "surah": 49, "verse": 13, "title": "Human Equality" },
      { "surah": 57, "verse": 25, "title": "Balance of Scale" },
      { "surah": 60, "verse": 8, "title": "Justice to All" },
      { "surah": 7, "verse": 29, "title": "Enjoin the Right" },
      { "surah": 4, "verse": 58, "title": "Restoring Trusts" },
      { "surah": 2, "verse": 188, "title": "Fair Dealing" },
      { "surah": 6, "verse": 152, "title": "Honest Weights" },
      { "surah": 17, "verse": 35, "title": "Giving Full Measure" },
      { "surah": 83, "verse": 1, "title": "The Defrauders" },
      { "surah": 42, "verse": 15, "title": "Equal Responsibility" },
      { "surah": 6, "verse": 115, "title": "Perfect Justice" },
      { "surah": 5, "verse": 42, "title": "Judging with Equity" }
    ]
  },
  {
    "id": "family",
    "title": "Family & Relationships",
    "description": "Heavenly guidance on parental respect, marriage, and kinship.",
    "image": "/assets/images/topics/family.png",
    "verses": [
      { "surah": 30, "verse": 21, "title": "Tranquility in Marriage" },
      { "surah": 17, "verse": 23, "title": "Kindness to Parents" },
      { "surah": 4, "verse": 1, "title": "Unity of Humanity" },
      { "surah": 2, "verse": 233, "title": "Infant Care" },
      { "surah": 31, "verse": 14, "title": "Gratitude to Parents" },
      { "surah": 66, "verse": 6, "title": "Protect your Family" },
      { "surah": 25, "verse": 74, "title": "Leaders of Righteous" },
      { "surah": 4, "verse": 34, "title": "Marital Harmony" },
      { "surah": 4, "verse": 36, "title": "Relatives and Neighbors" },
      { "surah": 46, "verse": 15, "title": "Burden of Mother" },
      { "surah": 2, "verse": 228, "title": "Rights of Women" },
      { "surah": 4, "verse": 11, "title": "Inheritance Justice" },
      { "surah": 60, "verse": 10, "title": "Marital Bonds" },
      { "surah": 2, "verse": 232, "title": "Family Reconciliation" }
    ]
  },
  {
    "id": "nature",
    "title": "Nature & Universe",
    "description": "Divine signs found in the creation of heavens, earth, and life.",
    "image": "/assets/images/topics/nature.png",
    "verses": [
      { "surah": 3, "verse": 190, "title": "Signs for Reflection" },
      { "surah": 30, "verse": 22, "title": "Diversity of Languages" },
      { "surah": 88, "verse": 17, "title": "Creation of Camel" },
      { "surah": 78, "verse": 6, "title": "Earth as a Bed" },
      { "surah": 21, "verse": 30, "title": "All Life from Water" },
      { "surah": 2, "verse": 164, "title": "Signs in Rainfall" },
      { "surah": 16, "verse": 66, "title": "Cattle and Milk" },
      { "surah": 6, "verse": 95, "title": "The Seed and Date" },
      { "surah": 13, "verse": 2, "title": "Floating Heavens" },
      { "surah": 55, "verse": 1, "title": "Balance of Ar-Rahman" },
      { "surah": 27, "verse": 60, "title": "Beautiful Orchards" },
      { "surah": 31, "verse": 27, "title": "The Seven Seas" },
      { "surah": 67, "verse": 3, "title": "Perfect Harmony" },
      { "surah": 22, "verse": 45, "title": "Ruined Cities" },
      { "surah": 16, "verse": 48, "title": "Shadows of Creation" }
    ]
  },
  {
    "id": "prayer",
    "title": "Prayer (Salah)",
    "description": "The spiritual lifeline and pillar connecting the soul to Allah.",
    "image": "/assets/images/topics/prayer.png",
    "verses": [
      { "surah": 2, "verse": 43, "title": "Bowing in Worship" },
      { "surah": 2, "verse": 45, "title": "Seeking Strength" },
      { "surah": 2, "verse": 110, "title": "Establish Prayer" },
      { "surah": 29, "verse": 45, "title": "Shield against Evil" },
      { "surah": 20, "verse": 14, "title": "To Remember Me" },
      { "surah": 4, "verse": 103, "title": "Defined Timings" },
      { "surah": 17, "verse": 78, "title": "Dawn Recitation" },
      { "surah": 23, "verse": 1, "title": "Humble Believers" },
      { "surah": 20, "verse": 132, "title": "Exemption and Trial" },
      { "surah": 2, "verse": 238, "title": "The Middle Prayer" },
      { "surah": 7, "verse": 170, "title": "Upholding the Book" },
      { "surah": 11, "verse": 114, "title": "Ends of the Day" },
      { "surah": 24, "verse": 56, "title": "Path to Mercy" },
      { "surah": 62, "verse": 9, "title": "Friday Assembly" },
      { "surah": 14, "verse": 40, "title": "Dua for Salah" }
    ]
  },
  {
    "id": "charity",
    "title": "Charity & Zakat",
    "description": "Purifying wealth through giving and supporting the underprivileged.",
    "image": "/assets/images/topics/charity.png",
    "verses": [
      { "surah": 2, "verse": 261, "title": "Multiplied Reward" },
      { "surah": 2, "verse": 271, "title": "Concealed Charity" },
      { "surah": 3, "verse": 92, "title": "Giving with Love" },
      { "surah": 9, "verse": 60, "title": "Social Support" },
      { "surah": 57, "verse": 18, "title": "The Beautiful Loan" },
      { "surah": 2, "verse": 274, "title": "Giving Day and Night" },
      { "surah": 63, "verse": 10, "title": "Before the End" },
      { "surah": 2, "verse": 110, "title": "Advancement for Soul" },
      { "surah": 51, "verse": 19, "title": "Right of the Needy" },
      { "surah": 9, "verse": 103, "title": "Purifier of Heart" },
      { "surah": 2, "verse": 270, "title": "Divine Watching" },
      { "surah": 4, "verse": 38, "title": "Ostentatious Giving" },
      { "surah": 30, "verse": 39, "title": "Increase of Riba" },
      { "surah": 76, "verse": 8, "title": "Feeding the Captive" },
      { "surah": 2, "verse": 215, "title": "Where to Spend" }
    ]
  },
  {
    "id": "knowledge",
    "title": "Knowledge & Wisdom",
    "description": "The noble pursuit of learning, reflection, and intellectual growth.",
    "image": "/assets/images/topics/knowledge.png",
    "verses": [
      { "surah": 96, "verse": 1, "title": "Read in His Name" },
      { "surah": 20, "verse": 114, "title": "Increase me in Knowledge" },
      { "surah": 39, "verse": 9, "title": "Equality of Intellect" },
      { "surah": 58, "verse": 11, "title": "Elevation of Scholars" },
      { "surah": 2, "verse": 269, "title": "Abundant Good" },
      { "surah": 35, "verse": 28, "title": "Awe of the Learned" },
      { "surah": 3, "verse": 18, "title": "Witnesses of Truth" },
      { "surah": 17, "verse": 36, "title": "Seeking Evidences" },
      { "surah": 16, "verse": 78, "title": "Heads of Hearing" },
      { "surah": 2, "verse": 31, "title": "Teaching the Names" },
      { "surah": 55, "verse": 1, "title": "Teacher of Al-Bayan" },
      { "surah": 9, "verse": 122, "title": "Journey for Study" },
      { "surah": 54, "verse": 17, "title": "Ease of Reminder" },
      { "surah": 68, "verse": 1, "title": "The Pen" },
      { "surah": 39, "verse": 18, "title": "Those who Listen" }
    ]
  },
  {
    "id": "repentance",
    "title": "Repentance & Mercy",
    "description": "The path of Tawbah and the boundless forgiveness of Al-Ghaffar.",
    "image": "/assets/images/topics/repentance.png",
    "verses": [
      { "surah": 39, "verse": 53, "title": "Do not Despair" },
      { "surah": 20, "verse": 82, "title": "Accepting Tawbah" },
      { "surah": 42, "verse": 25, "title": "Wiping out Sins" },
      { "surah": 66, "verse": 8, "title": "Sincere Return" },
      { "surah": 4, "verse": 110, "title": "Asking Forgiveness" },
      { "surah": 2, "verse": 222, "title": "Love for Penitent" },
      { "surah": 11, "verse": 3, "title": "Fruitful Living" },
      { "surah": 6, "verse": 54, "title": "Prescribed Mercy" },
      { "surah": 4, "verse": 17, "title": "Ignorant Wrongdoing" },
      { "surah": 24, "verse": 31, "title": "Public Repentance" },
      { "surah": 25, "verse": 70, "title": "Replacing Evil" },
      { "surah": 16, "verse": 119, "title": "Grace of Allah" },
      { "surah": 3, "verse": 133, "title": "Race to Forgiveness" },
      { "surah": 5, "verse": 39, "title": "Redemption" },
      { "surah": 4, "verse": 48, "title": "The Unforgivable" }
    ]
  },
  {
    "id": "afterlife",
    "title": "The Hereafter (Akhirah)",
    "description": "Eschewing the worldly for the eternal home of the soul.",
    "image": "/assets/images/topics/hereafter.png",
    "verses": [
      { "surah": 3, "verse": 185, "title": "Reality of Death" },
      { "surah": 56, "verse": 1, "title": "The Inevitable Event" },
      { "surah": 75, "verse": 1, "title": "The Resurrection" },
      { "surah": 78, "verse": 31, "title": "The Great Success" },
      { "surah": 39, "verse": 68, "title": "Trumpet Blast" },
      { "surah": 40, "verse": 16, "title": "Day of Exposure" },
      { "surah": 2, "verse": 4, "title": "Certainty of End" },
      { "surah": 50, "verse": 19, "title": "Agony of Death" },
      { "surah": 101, "verse": 1, "title": "The Striking Calamity" },
      { "surah": 69, "verse": 13, "title": "Sovereignty of Day" },
      { "surah": 82, "verse": 1, "title": "Cleaving Asunder" },
      { "surah": 81, "verse": 1, "title": "The Shrouding" },
      { "surah": 30, "verse": 11, "title": "Return to Him" },
      { "surah": 20, "verse": 102, "title": "Day of Blueing" },
      { "surah": 39, "verse": 73, "title": "Entry to Paradise" }
    ]
  },
  {
    "id": "prophets",
    "title": "Prophets & Messengers",
    "description": "The unbroken chain of divine guidance sent to all nations.",
    "image": "/assets/images/topics/prophets.png",
    "verses": [
      { "surah": 2, "verse": 136, "title": "Universal Brotherhood" },
      { "surah": 16, "verse": 36, "title": "Avoid False Deities" },
      { "surah": 33, "verse": 21, "title": "Excellent Pattern" },
      { "surah": 3, "verse": 84, "title": "Belief in All" },
      { "surah": 33, "verse": 40, "title": "Seal of Prophets" },
      { "surah": 12, "verse": 3, "title": "Beautiful Stories" },
      { "surah": 21, "verse": 107, "title": "Mercy for Worlds" },
      { "surah": 61, "verse": 6, "title": "Ahmad's Arrival" },
      { "surah": 4, "verse": 163, "title": "Chain of Revelation" },
      { "surah": 3, "verse": 144, "title": "Mortal Messengers" },
      { "surah": 2, "verse": 285, "title": "Faith in Message" },
      { "surah": 6, "verse": 84, "title": "Ancestry of Light" },
      { "surah": 19, "verse": 58, "title": "Prostrating Prophets" },
      { "surah": 21, "verse": 25, "title": "The Core Call" },
      { "surah": 10, "verse": 37, "title": "Verification" }
    ]
  },
  {
    "id": "truth",
    "title": "Truthfulness (Sidq)",
    "description": "Commitment to honesty and integrity in speech and action.",
    "image": "/assets/images/topics/truth.png",
    "verses": [
      { "surah": 9, "verse": 119, "title": "With the Truthful" },
      { "surah": 33, "verse": 70, "title": "Right Statement" },
      { "surah": 49, "verse": 15, "title": "True Belief" },
      { "surah": 2, "verse": 42, "title": "Mixing Falsehood" },
      { "surah": 17, "verse": 80, "title": "Entry of Truth" },
      { "surah": 3, "verse": 17, "title": "Patience and Truth" },
      { "surah": 33, "verse": 35, "title": "Truthful Men/Women" },
      { "surah": 5, "verse": 119, "title": "Benefit of Truth" },
      { "surah": 39, "verse": 33, "title": "Upholding Truth" },
      { "surah": 22, "verse": 30, "title": "Shunning Lies" },
      { "surah": 16, "verse": 105, "title": "The Liars" },
      { "surah": 12, "verse": 51, "title": "Confession" },
      { "surah": 10, "verse": 108, "title": "Following Truth" },
      { "surah": 34, "verse": 48, "title": "Hurling the Truth" },
      { "surah": 17, "verse": 81, "title": "Truth Triumphs" }
    ]
  },
  {
    "id": "fasting",
    "title": "Fasting (Ramadan)",
    "description": "The discipline of self-restraint and spiritual purification.",
    "image": "/assets/images/topics/fasting.png",
    "verses": [
      { "surah": 2, "verse": 183, "title": "Reason for Decree" },
      { "surah": 2, "verse": 184, "title": "Difficulty and Mercy" },
      { "surah": 2, "verse": 185, "title": "The Month of Quran" },
      { "surah": 2, "verse": 187, "title": "Nights of Ramadan" },
      { "surah": 33, "verse": 35, "title": "Devout Fasters" },
      { "surah": 2, "verse": 196, "title": "Hajj Fasting" },
      { "surah": 5, "verse": 89, "title": "Expiation Fast" },
      { "surah": 2, "verse": 186, "title": "Nearness of Allah" },
      { "surah": 19, "verse": 1, "title": "Dua of Zakariya" },
      { "surah": 19, "verse": 26, "title": "Fast of Silence" }
    ]
  },
  {
    "id": "creation",
    "title": "Creation & Purpose",
    "description": "Decoding the purpose and beauty of our existence.",
    "image": "/assets/images/topics/creation.png",
    "verses": [
      { "surah": 51, "verse": 56, "title": "Soul's Purpose" },
      { "surah": 7, "verse": 54, "title": "Perfect Order" },
      { "surah": 55, "verse": 14, "title": "Clay of Pottery" },
      { "surah": 23, "verse": 115, "title": "Not in Vain" },
      { "surah": 95, "verse": 4, "title": "Best of Stature" },
      { "surah": 2, "verse": 30, "title": "Earth's Custodian" },
      { "surah": 15, "verse": 26, "title": "Black Mud Formed" },
      { "surah": 38, "verse": 27, "title": "Divine Balance" },
      { "surah": 75, "verse": 36, "title": "Accountability" },
      { "surah": 32, "verse": 7, "title": "Spirit of Life" },
      { "surah": 40, "verse": 67, "title": "Stages of Life" },
      { "surah": 23, "verse": 12, "title": "Fluid of Existence" },
      { "surah": 6, "verse": 2, "title": "Prescribed Term" },
      { "surah": 36, "verse": 36, "title": "Creative Pairs" },
      { "surah": 17, "verse": 70, "title": "Dignity of Honor" }
    ]
  },
  {
    "id": "guidance",
    "title": "Guidance & Light",
    "description": "The Quran as a lighthouse and clear criterion for mankind.",
    "image": "/assets/images/topics/guidance.png",
    "verses": [
      { "surah": 1, "verse": 6, "title": "The Solid Path" },
      { "surah": 2, "verse": 2, "title": "Absolute Truth" },
      { "surah": 2, "verse": 185, "title": "Criterion of Faith" },
      { "surah": 3, "verse": 138, "title": "Exposition for All" },
      { "surah": 16, "verse": 89, "title": "Glad Tidings" },
      { "surah": 5, "verse": 15, "title": "Manifest Light" },
      { "surah": 17, "verse": 9, "title": "Most Upright Guide" },
      { "surah": 39, "verse": 23, "title": "Trembling Hearts" },
      { "surah": 6, "verse": 125, "title": "Chest to Islam" },
      { "surah": 10, "verse": 57, "title": "Healing for Hearts" },
      { "surah": 14, "verse": 1, "title": "Out of Darkness" },
      { "surah": 22, "verse": 54, "title": "Softened Souls" },
      { "surah": 32, "verse": 2, "title": "Lord of Worlds" },
      { "surah": 42, "verse": 52, "title": "Spirit of Light" },
      { "surah": 13, "verse": 27, "title": "Remembrance" }
    ]
  }
]